CONTRIBUTING.md
MANIFEST.in
README.rst
setup.py
docs/HISTORY.txt
docs/LICENSE.GPL
docs/LICENSE.txt
eea/__init__.py
eea.stringinterp.egg-info/PKG-INFO
eea.stringinterp.egg-info/SOURCES.txt
eea.stringinterp.egg-info/dependency_links.txt
eea.stringinterp.egg-info/entry_points.txt
eea.stringinterp.egg-info/namespace_packages.txt
eea.stringinterp.egg-info/not-zip-safe
eea.stringinterp.egg-info/requires.txt
eea.stringinterp.egg-info/top_level.txt
eea/stringinterp/README.txt
eea/stringinterp/__init__.py
eea/stringinterp/configure.zcml
eea/stringinterp/interfaces.py
eea/stringinterp/profiles.zcml
eea/stringinterp/setuphandlers.py
eea/stringinterp/version.txt
eea/stringinterp/adapters/__init__.py
eea/stringinterp/adapters/configure.zcml
eea/stringinterp/adapters/dollarReplace.py
eea/stringinterp/browser/__init__.py
eea/stringinterp/browser/configure.zcml
eea/stringinterp/locales/__init__.py
eea/stringinterp/locales/eea.pot
eea/stringinterp/locales/plone-manual.pot
eea/stringinterp/locales/update.sh
eea/stringinterp/locales/bg/LC_MESSAGES/eea.po
eea/stringinterp/locales/bg/LC_MESSAGES/plone.po
eea/stringinterp/locales/cs/LC_MESSAGES/eea.po
eea/stringinterp/locales/cs/LC_MESSAGES/plone.po
eea/stringinterp/locales/da/LC_MESSAGES/eea.po
eea/stringinterp/locales/da/LC_MESSAGES/plone.po
eea/stringinterp/locales/de/LC_MESSAGES/eea.po
eea/stringinterp/locales/de/LC_MESSAGES/plone.po
eea/stringinterp/locales/el/LC_MESSAGES/eea.po
eea/stringinterp/locales/el/LC_MESSAGES/plone.po
eea/stringinterp/locales/en/LC_MESSAGES/eea.po
eea/stringinterp/locales/en/LC_MESSAGES/plone.po
eea/stringinterp/locales/es/LC_MESSAGES/eea.po
eea/stringinterp/locales/es/LC_MESSAGES/plone.po
eea/stringinterp/locales/et/LC_MESSAGES/eea.po
eea/stringinterp/locales/et/LC_MESSAGES/plone.po
eea/stringinterp/locales/eu/LC_MESSAGES/eea.po
eea/stringinterp/locales/eu/LC_MESSAGES/plone.po
eea/stringinterp/locales/fi/LC_MESSAGES/eea.po
eea/stringinterp/locales/fi/LC_MESSAGES/plone.po
eea/stringinterp/locales/fr/LC_MESSAGES/eea.po
eea/stringinterp/locales/fr/LC_MESSAGES/plone.po
eea/stringinterp/locales/hr/LC_MESSAGES/eea.po
eea/stringinterp/locales/hr/LC_MESSAGES/plone.po
eea/stringinterp/locales/hu/LC_MESSAGES/eea.po
eea/stringinterp/locales/hu/LC_MESSAGES/plone.po
eea/stringinterp/locales/is/LC_MESSAGES/eea.po
